activitystreampython/__init__.py
activitystreampython/activitystream.py
activitystreampython-0.1.11.dist-info/LICENSE
activitystreampython-0.1.11.dist-info/METADATA
activitystreampython-0.1.11.dist-info/WHEEL
activitystreampython-0.1.11.dist-info/RECORD
