Metadata-Version: 2.1
Name: activitystreampython
Version: 0.1.11
Summary: A convenience library to make retrieving data from the Activity Stream Data Service API easier
Home-page: https://github.com/crowdengage/activitystreampython/
License: Apache-2.0
Author: Hugh Topping
Author-email: hugh@crowdengage.com
Requires-Python: >=3.9.5,<4.0.0
Classifier: License :: OSI Approved :: Apache Software License
Classifier: Programming Language :: Python :: 3
Classifier: Programming Language :: Python :: 3.10
Classifier: Programming Language :: Python :: 3.11
Requires-Dist: requests (>=2.31.0,<3.0.0)
Project-URL: Repository, https://github.com/crowdengage/activitystreampython/
